GPUmodules/GPUKeys.py
GPUmodules/GPUgui.py
GPUmodules/GPUmodule.py
GPUmodules/RegexPatterns.py
GPUmodules/__init__.py
GPUmodules/env.py
rickslab_gpu_utils-3.9.0.data/data/share/man/man1/gpu-chk.1
rickslab_gpu_utils-3.9.0.data/data/share/man/man1/gpu-ls.1
rickslab_gpu_utils-3.9.0.data/data/share/man/man1/gpu-mon.1
rickslab_gpu_utils-3.9.0.data/data/share/man/man1/gpu-pac.1
rickslab_gpu_utils-3.9.0.data/data/share/man/man1/gpu-plot.1
rickslab_gpu_utils-3.9.0.data/data/share/rickslab-gpu-utils/doc/LICENSE
rickslab_gpu_utils-3.9.0.data/data/share/rickslab-gpu-utils/doc/README.md
rickslab_gpu_utils-3.9.0.data/data/share/rickslab-gpu-utils/icons/gpu-mon.icon.png
rickslab_gpu_utils-3.9.0.data/data/share/rickslab-gpu-utils/icons/gpu-pac.icon.png
rickslab_gpu_utils-3.9.0.data/data/share/rickslab-gpu-utils/icons/gpu-plot.icon.png
rickslab_gpu_utils-3.9.0.data/scripts/gpu-chk
rickslab_gpu_utils-3.9.0.data/scripts/gpu-ls
rickslab_gpu_utils-3.9.0.data/scripts/gpu-mon
rickslab_gpu_utils-3.9.0.data/scripts/gpu-pac
rickslab_gpu_utils-3.9.0.data/scripts/gpu-plot
rickslab_gpu_utils-3.9.0.dist-info/LICENSE
rickslab_gpu_utils-3.9.0.dist-info/METADATA
rickslab_gpu_utils-3.9.0.dist-info/WHEEL
rickslab_gpu_utils-3.9.0.dist-info/top_level.txt
rickslab_gpu_utils-3.9.0.dist-info/RECORD
