Metadata-Version: 2.1
Name: rickslab-gpu-utils
Version: 3.9.0
Summary: Ricks-Lab GPU Utilities
Home-page: https://github.com/Ricks-Lab/gpu-utils
Author: RicksLab
Author-email: rueikes.homelab@gmail.com
License: GPL-3
Project-URL: Bug Tracker, https://github.com/Ricks-Lab/gpu-utils/issues
Project-URL: Documentation, https://github.com/Ricks-Lab/gpu-utils/blob/master/docs/USER_GUIDE.md
Project-URL: Source Code, https://github.com/Ricks-Lab/gpu-utils
Keywords: gpu system monitoring overclocking underclocking linux amdgpu nvidia-smi rocm amd nvidia opencl boinc
Platform: posix
Classifier: Development Status :: 5 - Production/Stable
Classifier: Operating System :: POSIX
Classifier: Natural Language :: English
Classifier: Programming Language :: Python :: 3
Classifier: Topic :: System :: Monitoring
Classifier: Environment :: GPU
Classifier: License :: OSI Approved :: GNU General Public License v3 (GPLv3)
Requires-Python: >=3.6
Requires-Dist: matplotlib (>=3.2.0)
Requires-Dist: pandas (>=1.1.0)
